{"is_source_file": true, "file_id": 7, "git_revision": "db9cd1d7288ab07ecc76da431430a1847bb28397", "state": 2, "description": "", "external_files": [], "external_methods": [], "published": [], "classes": [], "methods": [], "calls": [], "search-terms": [], "ctags": [], "hash": null, "format-version": 4, "code-base-name": "medical_decision_backend", "filename": "medical_decision_backend/api/migrations/__init__.py", "knowledge_revision": 23, "revision_history": [{"23": "db9cd1d7288ab07ecc76da431430a1847bb28397"}]}