{"is_source_file": false, "format": "", "description": "", "external_files": [], "external_methods": [], "published": [], "classes": [], "methods": [], "calls": [], "search-terms": [], "state": 2, "file_id": 1, "knowledge_revision": 54, "git_revision": "0a04cea3e7fd2d70ae190f2363910012d5298ad8", "hash": "8bd28d4830099b6a2730d2e86860d085", "format-version": 4, "code-base-name": "medical_decision_backend", "filename": "README.md", "revision_history": [{"54": "0a04cea3e7fd2d70ae190f2363910012d5298ad8"}]}